llama_prompter/__init__.py
llama_prompter/prompter.py
llama_prompter/py.typed
llama_prompter/types/__init__.py
llama_prompter/types/annotated.py
llama_prompter/types/base.py
llama_prompter/types/base_types.py
llama_prompter/types/dict.py
llama_prompter/types/list.py
llama_prompter/types/pydantic.py
llama_prompter/types/tuple.py
llama_prompter-0.2.2.dist-info/METADATA
llama_prompter-0.2.2.dist-info/WHEEL
llama_prompter-0.2.2.dist-info/RECORD
