Metadata-Version: 2.1
Name: llama-prompter
Version: 0.2.2
Summary: Prompt templating and structured LLM output for llama_cpp.
Home-page: https://gitlab.com/reginaldl/llama-prompter
License: MIT
Author: Reginald Lips
Author-email: reginald.l@gmail.com
Requires-Python: >=3.9,<4.0
Classifier: License :: OSI Approved :: MIT License
Classifier: Programming Language :: Python :: 3
Classifier: Programming Language :: Python :: 3.9
Classifier: Programming Language :: Python :: 3.10
Classifier: Programming Language :: Python :: 3.11
Classifier: Programming Language :: Python :: 3.12
Requires-Dist: pydantic (>=2.4.2,<3.0.0)
Project-URL: Repository, https://gitlab.com/reginaldl/llama-prompter
